neapolitan-stubs/__init__.pyi
neapolitan-stubs/views.pyi
neapolitan-stubs/management/__init__.pyi
neapolitan-stubs/management/commands/__init__.pyi
neapolitan-stubs/management/commands/mktemplate.pyi
neapolitan-stubs/templatetags/__init__.pyi
neapolitan-stubs/templatetags/neapolitan.pyi
neapolitan_stubs-25.0.dist-info/METADATA
neapolitan_stubs-25.0.dist-info/WHEEL
neapolitan_stubs-25.0.dist-info/licenses/LICENSE.txt
neapolitan_stubs-25.0.dist-info/RECORD
