Metadata-Version: 2.4
Name: neapolitan-stubs
Version: 25.0
Summary: Type stubs for the awesome Neapolitan package
Project-URL: Repository, https://github.com/nkantar/neapolitan-stubs
Author-email: Nik Kantar <nik@nkantar.com>
License: The MIT License (MIT)
License-File: LICENSE.txt
Classifier: Framework :: Django
Classifier: Intended Audience :: Developers
Classifier: License :: OSI Approved :: MIT License
Classifier: Programming Language :: Python :: 3.9
Classifier: Programming Language :: Python :: 3.10
Classifier: Programming Language :: Python :: 3.11
Classifier: Programming Language :: Python :: 3.12
Classifier: Programming Language :: Python :: 3.13
Classifier: Typing :: Stubs Only
Requires-Python: >=3.13.0
Requires-Dist: neapolitan>=24.8
